acore_db_app/__init__.py
acore_db_app/_version.py
acore_db_app/api.py
acore_db_app/cache.py
acore_db_app/compat.py
acore_db_app/logger.py
acore_db_app/orm.py
acore_db_app/orm_getter.py
acore_db_app/orm_tool.py
acore_db_app/paths.py
acore_db_app/app/__init__.py
acore_db_app/app/api.py
acore_db_app/app/locale.py
acore_db_app/app/quest.py
acore_db_app/cli/__init__.py
acore_db_app/cli/impl.py
acore_db_app/cli/main.py
acore_db_app/docs/__init__.py
acore_db_app/gui/__init__.py
acore_db_app/gui/main.py
acore_db_app/gui/tabs/__init__.py
acore_db_app/gui/tabs/main.py
acore_db_app/gui/tabs/quest_completer/__init__.py
acore_db_app/gui/tabs/quest_completer/main.py
acore_db_app/gui/tabs/quest_completer/query_form.py
acore_db_app/gui/tabs/quest_completer/quest_action.py
acore_db_app/gui/tabs/quest_completer/quest_selection.py
acore_db_app/gui/tabs/settings/__init__.py
acore_db_app/gui/tabs/settings/json_setting.py
acore_db_app/gui/tabs/settings/main.py
acore_db_app/gui/tabs/settings/setting_object.py
acore_db_app/sdk/__init__.py
acore_db_app/sdk/api.py
acore_db_app/sdk/quest.py
acore_db_app/tests/__init__.py
acore_db_app/tests/helper.py
acore_db_app/vendor/__init__.py
acore_db_app/vendor/nested_logger.py
acore_db_app/vendor/pytest_cov_helper.py
acore_db_app-0.2.4.dist-info/AUTHORS.rst
acore_db_app-0.2.4.dist-info/LICENSE.txt
acore_db_app-0.2.4.dist-info/METADATA
acore_db_app-0.2.4.dist-info/WHEEL
acore_db_app-0.2.4.dist-info/entry_points.txt
acore_db_app-0.2.4.dist-info/top_level.txt
acore_db_app-0.2.4.dist-info/RECORD
